impacket/Dot11Crypto.py
impacket/Dot11KeyManager.py
impacket/ICMP6.py
impacket/IP6.py
impacket/IP6_Address.py
impacket/IP6_Extension_Headers.py
impacket/ImpactDecoder.py
impacket/ImpactPacket.py
impacket/NDP.py
impacket/__init__.py
impacket/cdp.py
impacket/crypto.py
impacket/dhcp.py
impacket/dns.py
impacket/dot11.py
impacket/dpapi.py
impacket/eap.py
impacket/ese.py
impacket/helper.py
impacket/hresult_errors.py
impacket/mqtt.py
impacket/nmb.py
impacket/nt_errors.py
impacket/ntlm.py
impacket/pcap_linktypes.py
impacket/pcapfile.py
impacket/smb.py
impacket/smb3.py
impacket/smb3structs.py
impacket/smbconnection.py
impacket/smbserver.py
impacket/spnego.py
impacket/structure.py
impacket/system_errors.py
impacket/tds.py
impacket/uuid.py
impacket/version.py
impacket/winregistry.py
impacket/wps.py
impacket/dcerpc/__init__.py
impacket/dcerpc/v5/__init__.py
impacket/dcerpc/v5/atsvc.py
impacket/dcerpc/v5/bkrp.py
impacket/dcerpc/v5/dcomrt.py
impacket/dcerpc/v5/dhcpm.py
impacket/dcerpc/v5/drsuapi.py
impacket/dcerpc/v5/dtypes.py
impacket/dcerpc/v5/enum.py
impacket/dcerpc/v5/epm.py
impacket/dcerpc/v5/even.py
impacket/dcerpc/v5/even6.py
impacket/dcerpc/v5/lsad.py
impacket/dcerpc/v5/lsat.py
impacket/dcerpc/v5/mgmt.py
impacket/dcerpc/v5/mimilib.py
impacket/dcerpc/v5/ndr.py
impacket/dcerpc/v5/nrpc.py
impacket/dcerpc/v5/rpcrt.py
impacket/dcerpc/v5/rprn.py
impacket/dcerpc/v5/rrp.py
impacket/dcerpc/v5/samr.py
impacket/dcerpc/v5/sasec.py
impacket/dcerpc/v5/scmr.py
impacket/dcerpc/v5/srvs.py
impacket/dcerpc/v5/transport.py
impacket/dcerpc/v5/tsch.py
impacket/dcerpc/v5/wkst.py
impacket/dcerpc/v5/dcom/__init__.py
impacket/dcerpc/v5/dcom/comev.py
impacket/dcerpc/v5/dcom/oaut.py
impacket/dcerpc/v5/dcom/scmp.py
impacket/dcerpc/v5/dcom/vds.py
impacket/dcerpc/v5/dcom/wmi.py
impacket/examples/__init__.py
impacket/examples/logger.py
impacket/examples/os_ident.py
impacket/examples/remcomsvc.py
impacket/examples/secretsdump.py
impacket/examples/serviceinstall.py
impacket/examples/smbclient.py
impacket_py35-0.9.22.dev0.dist-info/LICENSE
impacket_py35-0.9.22.dev0.dist-info/METADATA
impacket_py35-0.9.22.dev0.dist-info/WHEEL
impacket_py35-0.9.22.dev0.dist-info/top_level.txt
impacket_py35-0.9.22.dev0.dist-info/RECORD
