Metadata-Version: 2.1
Name: impacket-py35
Version: 0.9.22.dev0
Summary: Network protocols Constructors and Dissectors
Home-page: https://www.secureauth.com/labs/open-source-tools/impacket
Author: SecureAuth Corporation
Author-email: oss@secureauth.com
Maintainer: Alberto Solino
Maintainer-email: bethus@gmail.com
License: Apache modified
Platform: Unix
Platform: Windows
Classifier: Programming Language :: Python :: 3.5
Classifier: Programming Language :: Python :: 3.6
Classifier: Programming Language :: Python :: 2.7
Classifier: Programming Language :: Python :: 2.6
Requires-Dist: pyasn1 (>=0.2.3)
Requires-Dist: pycryptodomex
Requires-Dist: pyOpenSSL (>=0.13.1)
Requires-Dist: six
Requires-Dist: ldap3 (==2.5.1)
Requires-Dist: ldapdomaindump (>=0.9.0)
Requires-Dist: flask (>=1.0)
Provides-Extra: pyreadline
Provides-Extra: python_version_2.7_
Requires-Dist: argparse ; extra == 'python_version_2.7_'
